asimov_nexus_module/__init__.py
asimov_nexus_module/importer/__init__.py
asimov_nexus_module/importer/__main__.py
asimov_nexus_module/importer/asimov-nexus-importer
asimov_nexus_module-0.0.0.dist-info/entry_points.txt
asimov_nexus_module-0.0.0.dist-info/METADATA
asimov_nexus_module-0.0.0.dist-info/WHEEL
asimov_nexus_module-0.0.0.dist-info/RECORD
