Metadata-Version: 2.1
Name: asimov-nexus-module
Version: 0.0.0
Summary: ASIMOV module for knowledge import powered by the ASIMOV.Nexus intelligence platform.
Author-email: ASIMOV Protocol <support@asimov.so>
Project-URL: Homepage, https://github.com/asimov-modules
Project-URL: Repository, https://github.com/asimov-modules/asimov-nexus-module
Project-URL: Changelog, https://github.com/asimov-modules/asimov-nexus-module/blob/master/CHANGES.md
Project-URL: Download, https://github.com/asimov-modules/asimov-nexus-module/releases/tag/0.0.0
Project-URL: Releases, https://github.com/asimov-modules/asimov-nexus-module/releases
Project-URL: Issues, https://github.com/asimov-modules/asimov-nexus-module/issues
Project-URL: Documentation, https://github.com/asimov-modules/asimov-nexus-module/blob/master/README.md
Keywords: asimov-module,asimov,ai
Classifier: Development Status :: 4 - Beta
Classifier: Environment :: Console
Classifier: Intended Audience :: Developers
Classifier: Intended Audience :: System Administrators
Classifier: Programming Language :: Python :: 3
Classifier: Programming Language :: Rust
Classifier: Topic :: Scientific/Engineering :: Artificial Intelligence
Classifier: Topic :: Software Development :: Libraries
Classifier: Topic :: Text Processing :: General
License: Unlicense
